README
_zephyr.pyx
setup.py
zephyr.py
PyZephyr.egg-info/PKG-INFO
PyZephyr.egg-info/SOURCES.txt
PyZephyr.egg-info/dependency_links.txt
PyZephyr.egg-info/top_level.txt