Metadata-Version: 1.1
Name: PyZephyr
Version: 0.2.0
Summary: PyZephyr - Python bindings for the Zephyr messaging library
Home-page: UNKNOWN
Author: Evan Broder
Author-email: broder@mit.edu
License: MIT
Platform: UNKNOWN
Requires: Pyrex
